MMsuit/MMapp.py
MMsuit/MMcalc.py
MMsuit/__init__.py
MMsuit-0.0.1.dist-info/LICENSE
MMsuit-0.0.1.dist-info/METADATA
MMsuit-0.0.1.dist-info/WHEEL
MMsuit-0.0.1.dist-info/top_level.txt
MMsuit-0.0.1.dist-info/RECORD
